{
  "DOCKER_MEMORY_USAGE_BYTES": {
    "defaultAggregate": "avg",
    "defaultResolutionMS": 1000,
    "description": "Docker Total memory usage",
    "displayName": "Docker Total memory usage",
    "displayNameShort": "DK MEM BYTES",
    "unit": "bytecount"
  },
  "DOCKER_MEMORY_LIMIT_BYTES": {
    "defaultAggregate": "avg",
    "defaultResolutionMS": 1000,
    "description": "Docker Total memory limit",
    "displayName": "Docker Total memory limit",
    "displayNameShort": "DK MEM LIMIT BYTES",
    "unit": "bytecount"
  },
  "DOCKER_MEMORY_USAGE_PERCENT": {
    "defaultAggregate": "avg",
    "defaultResolutionMS": 1000,
    "description": "Docker memory usage %",
    "displayName": "Docker  memory usage %",
    "displayNameShort": "DK MEM %",
    "unit": "percent"
  },
  "DOCKER_TOTAL_CPU_USAGE": {
    "defaultAggregate": "avg",
    "defaultResolutionMS": 1000,
    "description": "Total CPU usage",
    "displayName": "Docker total cpu usage",
    "displayNameShort": "DK TOTAL CPU",
    "unit": "percent"
  },
  "DOCKER_NETWORK_RX_BYTES": {
    "defaultAggregate": "avg",
    "defaultResolutionMS": 1000,
    "description": "Docker network i/o RX",
    "displayName": "Docker network i/o RX",
    "displayNameShort": "DK TOTAL NET RX BYTES",
    "unit": "bytecount"
  },
  "DOCKER_NETWORK_TX_BYTES": {
    "defaultAggregate": "avg",
    "defaultResolutionMS": 1000,
    "description": "Docker network i/o TX",
    "displayName": "Docker network i/o TX",
    "displayNameShort": "DK TOTAL NET TX BYTES",
    "unit": "bytecount"
  },
  "DOCKER_NETWORK_RX_PACKETS": {
    "defaultAggregate": "avg",
    "defaultResolutionMS": 1000,
    "description": "Docker network RX packets",
    "displayName": "Docker network RX packets'",
    "displayNameShort": "DK NET PCKTS RX",
    "unit": "number"
  },
  "DOCKER_NETWORK_TX_PACKETS": {
    "defaultAggregate": "avg",
    "defaultResolutionMS": 1000,
    "description": "Docker network TX packets",
    "displayName": "Docker network TX packets",
    "displayNameShort": "DK NET PCKTS RX",
    "unit": "number"
  },
  "DOCKER_NETWORK_RX_ERRORS": {
    "defaultAggregate": "avg",
    "defaultResolutionMS": 1000,
    "description": "Docker network RX errors",
    "displayName": "Docker network RX errors",
    "displayNameShort": "DK NET RX ERRORS",
    "unit": "number"
  },
  "DOCKER_NETWORK_TX_ERRORS": {
    "defaultAggregate": "avg",
    "defaultResolutionMS": 1000,
    "description": "Docker network TX errors",
    "displayName": "Docker network TX errors",
    "displayNameShort": "DK NET TX ERRORS",
    "unit": "number"
  }
}
